flags_be_client/__init__.py
flags_be_client/client.py
flags_be_client/test_client.py
feature_flags_client-1.0.77.dist-info/METADATA
feature_flags_client-1.0.77.dist-info/WHEEL
feature_flags_client-1.0.77.dist-info/RECORD
