Metadata-Version: 2.1
Name: feature-flags-client
Version: 1.0.77
Summary: 
Author: Stitch
Requires-Python: >=3.8,<4.0
Classifier: Programming Language :: Python :: 3
Classifier: Programming Language :: Python :: 3.8
Classifier: Programming Language :: Python :: 3.9
Classifier: Programming Language :: Python :: 3.10
Classifier: Programming Language :: Python :: 3.11
Requires-Dist: crc32c (>=2.3.post0,<3.0)
Requires-Dist: requests (==2.23.0)
